kmanga_mobi/__init__.py
kmanga_mobi/cache.py
kmanga_mobi/mobi.py
kmanga_mobi-0.1.0.dist-info/LICENSE.txt
kmanga_mobi-0.1.0.dist-info/WHEEL
kmanga_mobi-0.1.0.dist-info/METADATA
kmanga_mobi-0.1.0.dist-info/RECORD
