Metadata-Version: 2.1
Name: kmanga-mobi
Version: 0.1.0
Summary: mobi package extracted from kmanga
Home-page: https://github.com/whtsky/kmanga_mobi
License: GPL-3.0
Keywords: mobi
Author: Alberto Planas
Author-email: aplanas@gmail.com
Requires-Python: >=3.6,<4.0
Classifier: License :: OSI Approved :: GNU General Public License v3 (GPLv3)
Classifier: Programming Language :: Python :: 3
Classifier: Programming Language :: Python :: 3.6
Classifier: Programming Language :: Python :: 3.7
Classifier: Programming Language :: Python :: 3.8
Requires-Dist: pillow (>=6.2.1,<7.0.0)
Project-URL: Repository, https://github.com/whtsky/kmanga_mobi
